ws_week7.5/03_usonicSensor(brokeDown)/pwm.v
// 1. 상태를 정의함.
`define S0 0
`define S1 1
`define S2 2
// counter 수정 완.
// reset_b가 동작한 이후에 세기 시작하므로 한 클럭 느리게 동작하게 된다.
// `define COUNTER 


// 포트 인아웃 설정 및 와이어, 레지스터
module pwm (
    input clk,
    input resetb,
    input pen,
    input [3:0] duty,
    input [3:0] freq,

    output pwm
);


reg [1:0] state;
reg [1:0] next_state;



reg pwm;

reg [7:0] count;

always @(negedge resetb or posedge clk)
    if(~resetb)
        count <= 8'b0; 
    else if((state == `S1) || (state == `S2))
        count <= count + 1;
    else if(state == `S0)
        count <= 8'b0;



// 2. next state determination
always @(*)
    if( state == `S0)
        if (pen == 1'b1)
            next_state <= `S1;
        else
            next_state <= `S0;
    else if( state == `S1)
        if (count == duty )
            next_state <= `S2;
        else
            next_state <= `S1;
    else if( state == `S2)
        if (count == freq )
            next_state <= `S0;
        else
            next_state <= `S2;
    // else
    //     next_state <= state;

// 3. state change
always @(negedge resetb or posedge clk) begin
    if(~resetb)    
        state <= `S0;
    else
        state <= next_state;
end

// 4. output logic
always @(negedge resetb or posedge clk) begin
    if(~resetb)
        pwm <= 1'b0;
    else if((state == `S0)||(state == `S2))
        pwm <= 1'b0;
    else if(state == `S1)
        pwm <= 1'b1;
    
    
end

endmodule

ws_week7.5/03_usonicSensor(brokeDown)/usonic.v
`define U0 0
`define U1 1
`define U2 2



module usonic (
    input       clk,
    input       resetb,
    input [7:0] range,
    output      pwm
);


reg [1:0] state;
reg [1:0] next_state;

reg       pen;
reg [3:0] duty;

// next state
always @ (*)
    if (state == `U0)
        if(range<20 )
            next_state <= `U0;
        else if (range >100)
            next_state <= `U2;
        else 
            next_state <= `U1;
    else if (state == `U1)
        if(range<20 )
            next_state <= `U0;
        else if (range >100)
            next_state <= `U2;
        else 
            next_state <= `U1;
    else if (state == `U2)
        if(range<20 )
            next_state <= `U0;
        else if (range >100)
            next_state <= `U2;
        else 
            next_state <= `U1;
    // else
    //     next_state <= state;


// update state
always @(negedge resetb or posedge clk) begin
    if(~resetb)
        state <= `U0;
    else
        state <= next_state;
end


// output change (PEN, DUTY)

// PEN 출력 담당.
always @(negedge resetb or posedge clk) begin
    if(~resetb)
        pen <= 1'b0;
    else if ((state == `U1) || (state == `U2))
        pen <= 1'b1;
    else if(state == `U0)
        pen <= 1'b0;
end

// DUTY 출력 담당.
always @(negedge resetb or posedge clk) begin
    if(~resetb)
        duty <= 4'b0;
    else if (state == `U0)
        duty <= 4'b0;
    else if (state == `U1)
        duty <= 4'd5; // decimal
    else if (state == `U2)
        duty <= 4'd10; // decimal
end


pwm p1(
    .clk(clk),
    .resetb(resetb),
    .pen(pen),
    .duty(duty),
    .freq(4'd15),
    .pwm(pwm) // 출력은 그대로 받아오는 것임.


);


endmodule

ws_week7.5/03_usonicSensor(brokeDown)/tb.v
module tb_testbench;

// 하나의 freq가 끝나기 전에 duty가 바뀜 => count무한 증가 => pduty 추가

reg         CLK, RESETB;
reg [7:0]   RANGE;

wire        PWM;

usonic t1(
    .clk(CLK),
    .resetb(RESETB),
    .range(RANGE),
    
    .pwm(PWM)
);


initial begin // 초기화 구문
    CLK     = 1'b0;
    RESETB  = 1'b0;
    RANGE = 8'b0;

    #`FTIME;
    $finish;
end

always begin // 100ns period pulse
    #50 CLK = ~CLK; 
end


initial begin // test condition
    #150 RESETB = 1'b1; // reset release
    #200 RANGE = 8'd50;
    #2000 RANGE = 8'd200;
    #2000 RANGE = 8'd10;
    #2000 RANGE = 8'd100;

end


initial begin
    $dumpfile("sim.vcd");
    $dumpvars(0, tb_testbench);  
end


endmodule

ws_week7.5/03_usonicSensor(brokeDown)/sim.vcd
$date
	Wed May 03 20:37:24 2023
$end
$version
	Icarus Verilog
$end
$timescale
	1ps
$end
$scope module tb_testbench $end
$var wire 1 ! PWM $end
$var reg 1 " CLK $end
$var reg 8 # RANGE [7:0] $end
$var reg 1 $ RESETB $end
$scope module t1 $end
$var wire 1 " clk $end
$var wire 8 % range [7:0] $end
$var wire 1 $ resetb $end
$var wire 1 ! pwm $end
$var reg 4 & duty [3:0] $end
$var reg 2 ' next_state [1:0] $end
$var reg 1 ( pen $end
$var reg 2 ) state [1:0] $end
$scope module p1 $end
$var wire 1 " clk $end
$var wire 4 * duty [3:0] $end
$var wire 4 + freq [3:0] $end
$var wire 1 ( pen $end
$var wire 1 $ resetb $end
$var reg 8 , count [7:0] $end
$var reg 2 - next_state [1:0] $end
$var reg 1 ! pwm $end
$var reg 2 . state [1:0] $end
$upscope $end
$upscope $end
$upscope $end
$enddefinitions $end
#0
$dumpvars
b0 .
b0 -
b0 ,
b1111 +
b0 *
b0 )
0(
b0 '
b0 &
b0 %
0$
b0 #
0"
0!
$end
#50000
1"
#100000
0"
#150000
1"
1$
#200000
0"
#250000
1"
#300000
0"
#350000
b1 '
1"
b110010 #
b110010 %
#400000
0"
#450000
b1 )
1"
#500000
0"
#550000
b1 -
1(
b101 &
b101 *
1"
#600000
0"
#650000
b1 .
1"
#700000
0"
#750000
b1 ,
1!
1"
#800000
0"
#850000
b10 ,
1"
#900000
0"
#950000
b11 ,
1"
#1000000
0"
#1050000
b100 ,
1"
#1100000
0"
#1150000
b10 -
b101 ,
1"
#1200000
0"
#1250000
b10 .
b110 ,
1"
#1300000
0"
#1350000
b111 ,
0!
1"
#1400000
0"
#1450000
b1000 ,
1"
#1500000
0"
#1550000
b1001 ,
1"
#1600000
0"
#1650000
b1010 ,
1"
#1700000
0"
#1750000
b1011 ,
1"
#1800000
0"
#1850000
b1100 ,
1"
#1900000
0"
#1950000
b1101 ,
1"
#2000000
0"
#2050000
b1110 ,
1"
#2100000
0"
#2150000
b0 -
b1111 ,
1"
#2200000
0"
#2250000
b1 -
b0 .
b10000 ,
1"
#2300000
0"
#2350000
b0 ,
b1 .
b10 '
1"
b11001000 #
b11001000 %
#2400000
0"
#2450000
b10 )
1!
b1 ,
1"
#2500000
0"
#2550000
b10 ,
b1010 &
b1010 *
1"
#2600000
0"
#2650000
b11 ,
1"
#2700000
0"
#2750000
b100 ,
1"
#2800000
0"
#2850000
b101 ,
1"
#2900000
0"
#2950000
b110 ,
1"
#3000000
0"
#3050000
b111 ,
1"
#3100000
0"
#3150000
b1000 ,
1"
#3200000
0"
#3250000
b1001 ,
1"
#3300000
0"
#3350000
b10 -
b1010 ,
1"
#3400000
0"
#3450000
b10 .
b1011 ,
1"
#3500000
0"
#3550000
b1100 ,
0!
1"
#3600000
0"
#3650000
b1101 ,
1"
#3700000
0"
#3750000
b1110 ,
1"
#3800000
0"
#3850000
b0 -
b1111 ,
1"
#3900000
0"
#3950000
b1 -
b10000 ,
b0 .
1"
#4000000
0"
#4050000
b1 .
b0 ,
1"
#4100000
0"
#4150000
b1 ,
1!
1"
#4200000
0"
#4250000
b10 ,
1"
#4300000
0"
#4350000
b11 ,
b0 '
1"
b1010 #
b1010 %
#4400000
0"
#4450000
b0 )
b100 ,
1"
#4500000
0"
#4550000
b101 ,
0(
b0 &
b0 *
1"
#4600000
0"
#4650000
b110 ,
1"
#4700000
0"
#4750000
b111 ,
1"
#4800000
0"
#4850000
b1000 ,
1"
#4900000
0"
#4950000
b1001 ,
1"
#5000000
0"
#5050000
b1010 ,
1"
#5100000
0"
#5150000
b1011 ,
1"
#5200000
0"
#5250000
b1100 ,
1"
#5300000
0"
#5350000
b1101 ,
1"
#5400000
0"
#5450000
b1110 ,
1"
#5500000
0"
#5550000
b1111 ,
1"
#5600000
0"
#5650000
b10000 ,
1"
#5700000
0"
#5750000
b10001 ,
1"
#5800000
0"
#5850000
b10010 ,
1"
#5900000
0"
#5950000
b10011 ,
1"
#6000000
0"
#6050000
b10100 ,
1"
#6100000
0"
#6150000
b10101 ,
1"
#6200000
0"
#6250000
b10110 ,
1"
#6300000
0"
#6350000
b10111 ,
b1 '
1"
b1100100 #
b1100100 %
#6400000
0"
#6450000
b1 )
b11000 ,
1"
#6500000
0"
#6550000
b11001 ,
1(
b101 &
b101 *
1"
#6600000
0"
#6650000
b11010 ,
1"
#6700000
0"
#6750000
b11011 ,
1"
#6800000
0"
#6850000
b11100 ,
1"
#6900000
0"
#6950000
b11101 ,
1"
#7000000
0"
#7050000
b11110 ,
1"
#7100000
0"
#7150000
b11111 ,
1"
#7200000
0"
#7250000
b100000 ,
1"
#7300000
0"
#7350000
b100001 ,
1"
#7400000
0"
#7450000
b100010 ,
1"
#7500000
0"
#7550000
b100011 ,
1"
#7600000
0"
#7650000
b100100 ,
1"
#7700000
0"
#7750000
b100101 ,
1"
#7800000
0"
#7850000
b100110 ,
1"
#7900000
0"
#7950000
b100111 ,
1"
#8000000
0"
#8050000
b101000 ,
1"
#8100000
0"
#8150000
b101001 ,
1"
#8200000
0"
#8250000
b101010 ,
1"
#8300000
0"
#8350000
b101011 ,
1"
#8400000
0"
#8450000
b101100 ,
1"
#8500000
0"
#8550000
b101101 ,
1"
#8600000
0"
#8650000
b101110 ,
1"
#8700000
0"
#8750000
b101111 ,
1"
#8800000
0"
#8850000
b110000 ,
1"
#8900000
0"
#8950000
b110001 ,
1"
#9000000
0"
#9050000
b110010 ,
1"
#9100000
0"
#9150000
b110011 ,
1"
#9200000
0"
#9250000
b110100 ,
1"
#9300000
0"
#9350000
b110101 ,
1"
#9400000
0"
#9450000
b110110 ,
1"
#9500000
0"
#9550000
b110111 ,
1"
#9600000
0"
#9650000
b111000 ,
1"
#9700000
0"
#9750000
b111001 ,
1"
#9800000
0"
#9850000
b111010 ,
1"
#9900000
0"
#9950000
b111011 ,
1"
