ws_week4/02_ALU/ALU.v
module ALU(
    input [1:0] cmd,
    input [3:0] a,
    input [3:0] b,
    output [3:0] out
);



// add의 결과.
wire [3:0] RES_ADD; 
wire C_OUT;
wire B_OUT;



// and의 결과.
wire [3:0] RES_AND; 
// or의 결과.
wire [3:0] RES_OR;
// sub의 결과.
wire [3:0] RES_SUB; 



// C_OUT 과 RESADD 에 a+b를 할당.
assign {C_OUT, RES_ADD} = a+b;
// RESAND에 a and b 할당.
assign RES_AND = a&b;

assign RES_OR = a|b;

assign {B_OUT, RES_SUB} = a-b;



// 삼항연산자 : (out) = (조건) ? (참일때출력) : (거짓일때출력);
assign out = 
    (cmd == 2'b00) ? RES_AND : 
    (cmd == 2'b01) ? RES_OR : 
    (cmd == 2'b10) ? RES_ADD :
    (cmd == 2'b11) ? RES_SUB : 4'b0000;

endmodule

ws_week4/02_ALU/tb.v
module tb;

reg [1:0] CMD;
reg [3:0] A;
reg [3:0] B;

wire [3:0] OUT;

ALU dut1(
    .cmd(CMD),
    .a(A),
    .b(B),
    .out(OUT)
);


initial begin 
    #100
    CMD = 2'b10; // cmd 4 add
    A = 4'h3;
    B = 4'h5;
    
    #100
    CMD = 2'b00;
    
    #100
    CMD = 2'b01;
    
    #100
    CMD = 2'b11;

    #100
    A = 4'hA;
    B = 4'h5;
    #100
    A = 4'hA;
    B = 4'b1111;
    #100
    A = 4'b1111;
    B = 4'hA;
end

initial begin
    $monitor("tick : %0d, a : %b, b : %b", $time, A, B); 
    #800;
    $finish;
end

initial begin
    $dumpfile("sim.vcd");
    $dumpvars(0,dut1);
end

endmodule

ws_week4/02_ALU/sim.vcd
$date
	Fri Mar 31 08:48:55 2023
$end
$version
	Icarus Verilog
$end
$timescale
	1s
$end
$scope module tb $end
$scope module dut1 $end
$var wire 4 ! RES_AND [3:0] $end
$var wire 4 " RES_OR [3:0] $end
$var wire 4 # a [3:0] $end
$var wire 4 $ b [3:0] $end
$var wire 2 % cmd [1:0] $end
$var wire 4 & out [3:0] $end
$var wire 4 ' RES_SUB [3:0] $end
$var wire 4 ( RES_ADD [3:0] $end
$var wire 1 ) C_OUT $end
$var wire 1 * B_OUT $end
$upscope $end
$upscope $end
$enddefinitions $end
#0
$dumpvars
x*
x)
bx (
bx '
bx &
bx %
bx $
bx #
bx "
bx !
$end
#100
b1000 &
b1000 (
0)
b1110 '
1*
b1 !
b111 "
b101 $
b11 #
b10 %
#200
b1 &
b0 %
#300
b111 &
b1 %
#400
b1110 &
b11 %
#500
b101 &
b0 !
b1111 "
b1111 (
b101 '
0*
b1010 #
#600
b1011 &
b1010 !
b1001 (
1)
b1011 '
1*
b1111 $
#700
b101 &
b101 '
0*
b1010 $
b1111 #
