ws_week7.5/01_TrafficLight/traffic.v
// 1. 상태를 정의함.
`define S0 2'b00 // 가로방향 초록불 (세로방향 빨강불)
`define S1 2'b01 // 가로방향 노랑불 (세로방향 빨강불)
`define S2 2'b10 // 가로방향 빨강불 (세로방향 초록불)
`define S3 2'b11 // 가로방향 빨강불 (세로방향 노랑불) 가로방향(L0) 세로방향(L1)

`define RED     0
`define YELLOW  1
`define GREEN   2 // Q. 이건 몇 비트임?


// 포트 인아웃 설정 및 와이어, 레지스터
module traffic (
    input clk,
    input resetb,
    input car0,
    input car1,

    output [1:0] led0, // 여기다가 비트 지정해도 되긴하지. 이게 더 편한가?
    output [1:0] led1
);
    reg [1:0] state;
    reg [1:0] next_state;
    reg [1:0] led0; // Q. 왜 중복해서 비트를 정의해주지..?
    reg [1:0] led1;

// 2. next state determination
    always @(*)
        if(state == `S0)
            if(car0 == 1'b0)
                next_state <= `S1;
            else
                next_state <= `S0;
        else if(state == `S1)
            next_state <= `S2;
        else if(state == `S2)
            if(car1 == 1'b0)
                next_state <= `S3;
            else
                next_state <= `S2;
        else if(state == `S3)
            next_state <= `S0;
        else
            next_state <= state;
    
// 3. state change
    always @(negedge resetb or posedge clk)
        if(~resetb)
            state <= `S0; // initial state
        else
            state <= next_state; // update from next_state

// 4. output logic
// led0과 led1을 같이 하면 안 된다. 다른 always 구문을 이용.
// 코딩언어가 아닌 하드웨어를 기술하는 언어.
// 하나의 reg가 하나의 플립플롭.
// state에 따라 구름(always)에서 플립플롭에 신호를 넣어줌.
// 하나의 always에는 하나의 레지스터만 사용해야(건드려야)한다.
always @(negedge resetb or posedge clk) begin
    if(~resetb)
        led0 <= 2'b0;
        // led1 <= 2'b0;
    else if(state == `S0)
        led0 <= `GREEN;
        // led1 <= `RED;
    else if(state == `S1)
        led0 <= `YELLOW;
        // led1 <= `RED;
    else if(state == `S2)
        led0 <= `RED;
        // led1 <= `GREEN;
    else if(state == `S3)
        led0 <= `RED;
        // led1 <= `YELLOW;
    else
        led0 <= 2'b0;
        // led1 <= 2'b0;
end

always @(negedge resetb or posedge clk) begin
    if(~resetb)
        led1 <= 2'b0;
    else if(state == `S0)
        led1 <= `RED;
    else if(state == `S1)
        led1 <= `RED;
    else if(state == `S2)
        led1 <= `GREEN;
    else if(state == `S3)
        led1 <= `YELLOW;
    else
        led1 <= 2'b0;
end

endmodule

ws_week7.5/01_TrafficLight/tb.v
module tb_testbench;

// led는 state에 비해 한 클럭 늦게 동작하는거 맞다. 어쩔 수 없음.

reg CLK, RESETB;
reg CAR0, CAR1;

wire [1:0] LED0;
wire [1:0] LED1;

traffic t1(
    .clk(CLK),
    .resetb(RESETB),
    .car0(CAR0),
    .car1(CAR1),
    .led0(LED0),
    .led1(LED1)
);

initial begin
    CLK     = 1'b0;
    RESETB  = 1'b0;
    CAR0 = 1'b0;
    CAR1 = 1'b0;

    $monitor($time, CLK,  RESETB, CAR0, LED0, CAR0, LED1);

    #`FTIME;
    $finish;
end

always begin
    #50 CLK = ~CLK; // 100ns period pulse
end

// test condition
initial begin
    #150 RESETB = 1'b1; // reset release
    CAR0 = 1'b1;
    CAR1 = 1'b0;    // S0
    
    #500;
    CAR0 = 1'b1;
    CAR1 = 1'b1;    // S0
    
    #500;
    CAR0 = 1'b0;
    CAR1 = 1'b1;    // S0 => S1 => S2

    #500;
    CAR0 = 1'b0;
    CAR1 = 1'b0;    // S2 => S3 => S0

end


initial begin
    $dumpfile("sim.vcd");
    $dumpvars(0, tb_testbench);  
end


endmodule

ws_week7.5/01_TrafficLight/sim.vcd
$date
	Wed May 03 18:55:24 2023
$end
$version
	Icarus Verilog
$end
$timescale
	1ps
$end
$scope module tb_testbench $end
$var wire 2 ! LED1 [1:0] $end
$var wire 2 " LED0 [1:0] $end
$var reg 1 # CAR0 $end
$var reg 1 $ CAR1 $end
$var reg 1 % CLK $end
$var reg 1 & RESETB $end
$scope module t1 $end
$var wire 1 # car0 $end
$var wire 1 $ car1 $end
$var wire 1 % clk $end
$var wire 1 & resetb $end
$var reg 2 ' led0 [1:0] $end
$var reg 2 ( led1 [1:0] $end
$var reg 2 ) next_state [1:0] $end
$var reg 2 * state [1:0] $end
$upscope $end
$upscope $end
$enddefinitions $end
#0
$dumpvars
b0 *
b1 )
b0 (
b0 '
0&
0%
0$
0#
b0 "
b0 !
$end
#50000
1%
#100000
0%
#150000
b1 *
b10 "
b10 '
b10 )
1%
1#
1&
#200000
0%
#250000
b11 )
b1 "
b1 '
b10 *
1%
#300000
0%
#350000
b0 )
b11 *
b0 "
b0 '
b10 !
b10 (
1%
#400000
0%
#450000
b1 !
b1 (
b0 *
1%
#500000
0%
#550000
b10 "
b10 '
b0 !
b0 (
1%
#600000
0%
#650000
1%
1$
#700000
0%
#750000
1%
#800000
0%
#850000
1%
#900000
0%
#950000
1%
#1000000
0%
#1050000
1%
#1100000
0%
#1150000
b1 )
1%
0#
#1200000
0%
#1250000
b10 )
b1 *
1%
#1300000
0%
#1350000
b10 *
b1 "
b1 '
1%
#1400000
0%
#1450000
b10 !
b10 (
b0 "
b0 '
1%
#1500000
0%
#1550000
1%
#1600000
0%
#1650000
b11 )
1%
0$
#1700000
0%
#1750000
b0 )
b11 *
1%
#1800000
0%
#1850000
b1 )
b1 !
b1 (
b0 *
1%
#1900000
0%
#1950000
b10 )
b1 *
b10 "
b10 '
b0 !
b0 (
1%
#2000000
0%
#2050000
b11 )
b1 "
b1 '
b10 *
1%
#2100000
0%
#2150000
b0 )
b11 *
b0 "
b0 '
b10 !
b10 (
1%
#2200000
0%
#2250000
b1 )
b1 !
b1 (
b0 *
1%
#2300000
0%
#2350000
b10 )
b1 *
b10 "
b10 '
b0 !
b0 (
1%
#2400000
0%
#2450000
b11 )
b1 "
b1 '
b10 *
1%
#2500000
0%
#2550000
b0 )
b11 *
b0 "
b0 '
b10 !
b10 (
1%
#2600000
0%
#2650000
b1 )
b1 !
b1 (
b0 *
1%
#2700000
0%
#2750000
b10 )
b1 *
b10 "
b10 '
b0 !
b0 (
1%
#2800000
0%
#2850000
b11 )
b1 "
b1 '
b10 *
1%
#2900000
0%
#2950000
b0 )
b11 *
b0 "
b0 '
b10 !
b10 (
1%
