ws_week8/01_stack copy/stack.v
/*
STACK : buffer에 PUSH를 주면 데이터가 하나씩 쌓이고, POP을 주면 마지막 데이터 나온다. LIFO
QUEUE : FIFO
*/

module stack (
    input       clk,
    input       resetb,

    input [7:0] datain,
    input       push, // 데이터 입력을 위한 push 명령어

    output [7:0] dataout,
    input        pop,

    // 스택의 상태를 알려주는 역할
    output       full,
    output       empty
);
reg [7:0] dataout;

// stack pointer를 만듬. 
reg [4:0] sp;          // 현재 buffer가 어디에 왔는지. 8개 버퍼이니 3비트.

// assign 사용을 위해 wire로 만듬.
wire full;
assign full = (sp == 8) ? 1'b1 : 1'b0; // 아래 참고.
// full 과 비슷하게 만들면 됨.
wire empty;
assign empty = (sp == 0) ? 1'b1 : 1'b0; // 8개까지 왔다면 버퍼7번이다. (0부터 있음)


/*
// 버퍼를 만듬과 버퍼의 크기를 설정
reg [7:0] buffer[0:7]; // 8비트가 0~7까지 8개 있다 = 버퍼가 8개다.
위험한? 코드니까 아래처럼 하라고 하네.
*/
reg [7:0] buffer0;
reg [7:0] buffer1;
reg [7:0] buffer2;
reg [7:0] buffer3;
reg [7:0] buffer4;
reg [7:0] buffer5;
reg [7:0] buffer6;
reg [7:0] buffer7;

// always 안에서 계산하지 말자. 조건은 밖에서 처리하도록.
wire writeen;
wire outputen;
assign writeen = push & !full;
assign outputen = pop & !empty;

// stack pointer의 동작
always @(posedge clk or negedge resetb ) begin
    if(~resetb)
        sp <= 0;
    else if(writeen)
        sp <= sp + 1;
    else if(outputen)
        sp <= sp - 1;
end




/*
// push 동작
always @(posedge clk or negedge resetb) begin
    if(~resetb)
        buffer[sp] <= 0;
    else if(writeen)
        buffer[sp] <= datain;
end
*/
wire buffer0_en;
assign buffer0_en = (sp == 0) & writeen;
always @(posedge clk or negedge resetb) begin
    if(~resetb)
        buffer0 <= 0;
    else if(buffer0_en)
        buffer0 <= datain;
end
wire buffer1_en;
assign buffer1_en = (sp == 1) & writeen;
always @(posedge clk or negedge resetb) begin
    if(~resetb)
        buffer1 <= 0;
    else if(buffer1_en)
        buffer1 <= datain;
end
wire buffer2_en;
assign buffer2_en = (sp == 2) & writeen;
always @(posedge clk or negedge resetb) begin
    if(~resetb)
        buffer2 <= 0;
    else if(buffer2_en)
        buffer2 <= datain;
end
wire buffer3_en;
assign buffer3_en = (sp == 3) & writeen;
always @(posedge clk or negedge resetb) begin
    if(~resetb)
        buffer3 <= 0;
    else if(buffer3_en)
        buffer3 <= datain;
end
wire buffer4_en;
assign buffer4_en = (sp == 4) & writeen;
always @(posedge clk or negedge resetb) begin
    if(~resetb)
        buffer4 <= 0;
    else if(buffer4_en)
        buffer4 <= datain;
end
wire buffer5_en;
assign buffer5_en = (sp == 5) & writeen;
always @(posedge clk or negedge resetb) begin
    if(~resetb)
        buffer5 <= 0;
    else if(buffer5_en)
        buffer5 <= datain;
end
wire buffer6_en;
assign buffer6_en = (sp == 6) & writeen;
always @(posedge clk or negedge resetb) begin
    if(~resetb)
        buffer6 <= 0;
    else if(buffer6_en)
        buffer6 <= datain;
end
wire buffer7_en;
assign buffer7_en = (sp == 7) & writeen;
always @(posedge clk or negedge resetb) begin
    if(~resetb)
        buffer7 <= 0;
    else if(buffer7_en)
        buffer7 <= datain;
end




/*
// pop 동작
always @(posedge clk or negedge resetb) begin
    if( ~resetb)
        dataout <= 0;
    else if(outputen)
        dataout <= buffer[sp];
end
*/
wire out0_en;
assign out0_en = (sp == 1) & outputen;

// always @(posedge clk or negedge resetb) begin
//     if(~resetb)
//         buffer0 <= 0;
//     else if(buffer7_en)
//         buffer0 <= datain;
// end
wire out1_en;
assign out1_en = (sp == 2) & outputen;
// always @(posedge clk or negedge resetb) begin
//     if(~resetb)
//         buffer1 <= 0;
//     else if(buffer1_en)
//         buffer1 <= datain;
// end
wire out2_en;
assign out2_en = (sp == 3) & outputen;
// always @(posedge clk or negedge resetb) begin
//     if(~resetb)
//         buffer2 <= 0;
//     else if(buffer2_en)
//         buffer2 <= datain;
// end
wire out3_en;
assign out3_en = (sp == 4) & outputen;
// always @(posedge clk or negedge resetb) begin
//     if(~resetb)
//         buffer3 <= 0;
//     else if(buffer3_en)
//         buffer3 <= datain;
// end
wire out4_en;
assign out4_en = (sp == 5) & outputen;
// always @(posedge clk or negedge resetb) begin
//     if(~resetb)
//         buffer4 <= 0;
//     else if(buffer4_en)
//         buffer4 <= datain;
// end
wire out5_en;
assign out5_en = (sp == 6) & outputen;
// always @(posedge clk or negedge resetb) begin
//     if(~resetb)
//         buffer5 <= 0;
//     else if(buffer5_en)
//         buffer5 <= datain;
// end
wire out6_en;
assign out6_en = (sp == 7) & outputen;
// always @(posedge clk or negedge resetb) begin
//     if(~resetb)
//         buffer6 <= 0;
//     else if(buffer7_en)
//         buffer6 <= datain;
// end
wire out7_en;
assign out7_en = (sp == 8) & outputen;
// always @(posedge clk or negedge resetb) begin
//     if(~resetb)
//         buffer7 <= 0;
//     else if(buffer7_en)
//         buffer7 <= datain;
// end

always@(negedge resetb or posedge clk)
    if(~resetb)
        dataout <= 0;
    else if(out0_en)
        dataout <= buffer0;
    else if(out1_en)
        dataout <= buffer1;
    else if(out2_en)
        dataout <= buffer2;
    else if(out3_en)
        dataout <= buffer3;
    else if(out4_en)
        dataout <= buffer4;
    else if(out5_en)
        dataout <= buffer5;
    else if(out6_en)
        dataout <= buffer6;
    else if(out7_en)
        dataout <= buffer7;


/*
assign dataout = (out0_en) ? buffer0 :
                 (out1_en) ? buffer1 :
                 (out2_en) ? buffer2 :
                 (out3_en) ? buffer3 :
                 (out4_en) ? buffer4 :
                 (out5_en) ? buffer5 :
                 (out6_en) ? buffer6 :
                 (out7_en) ? buffer7 : 0; */

/*
동작조건 이상하게 하지말자..
always @(posedge clk & negedge resetb) begin
    => always @(posedge clk or negedge resetb) begin
*/


endmodule


/*
sp는 데이터 넣고 +1 되므로 버퍼7번까지 데이터 8개 넣으면 얘는 8이 되어있다. 
따라서 7인줄 알았는데 8이고, 따라서 4비트가 필요하다.
*/

ws_week8/01_stack copy/tb.v
module tb_testbench;

reg         CLK, RESETB;


stack t1(
    .clk(CLK),
    .resetb(RESETB),
    .datain(DATAIN),
    .push(PUSH),
    .dataout(DATAOUT),
    .pop(POP),
    .full(FULL),
    .empty(EMPTY)
);

reg [7:0] DATAIN;
reg PUSH, POP;
wire [7:0] DATAOUT;
wire FULL, EMPTY;


initial begin // 초기화 구문
    CLK     = 1'b0;
    RESETB  = 1'b0;
    DATAIN = 0; PUSH = 0; POP = 0;

    #`FTIME;
    $finish;
end

always begin // 100ns period pulse
    #50 CLK = ~CLK; 
end

initial begin
    $dumpfile("sim.vcd");
    $dumpvars(0, tb_testbench);  
end

initial begin // test condition
    #100 RESETB = 1'b1; // reset release

    #100 DATAIN = 10; PUSH = 1;
    #100 DATAIN = 20;
    #100 DATAIN = 30;
    #100 DATAIN = 40;
    #100 DATAIN = 50;
    #100 DATAIN = 60;
    #100 DATAIN = 70;
    #100 DATAIN = 80;
    #100 DATAIN = 90;
    #100 PUSH = 0;
    #100 POP = 1;
    // #100 POP = 0;
end




endmodule

ws_week8/01_stack copy/sim.vcd
$date
	Fri May 12 15:56:30 2023
$end
$version
	Icarus Verilog
$end
$timescale
	1ps
$end
$scope module tb_testbench $end
$var wire 1 ! FULL $end
$var wire 1 " EMPTY $end
$var wire 8 # DATAOUT [7:0] $end
$var reg 1 $ CLK $end
$var reg 8 % DATAIN [7:0] $end
$var reg 1 & POP $end
$var reg 1 ' PUSH $end
$var reg 1 ( RESETB $end
$scope module t1 $end
$var wire 1 ) buffer0_en $end
$var wire 1 * buffer1_en $end
$var wire 1 + buffer2_en $end
$var wire 1 , buffer3_en $end
$var wire 1 - buffer4_en $end
$var wire 1 . buffer5_en $end
$var wire 1 / buffer6_en $end
$var wire 1 0 buffer7_en $end
$var wire 1 $ clk $end
$var wire 8 1 datain [7:0] $end
$var wire 1 2 out0_en $end
$var wire 1 3 out1_en $end
$var wire 1 4 out2_en $end
$var wire 1 5 out3_en $end
$var wire 1 6 out4_en $end
$var wire 1 7 out5_en $end
$var wire 1 8 out6_en $end
$var wire 1 9 out7_en $end
$var wire 1 : outputen $end
$var wire 1 & pop $end
$var wire 1 ' push $end
$var wire 1 ( resetb $end
$var wire 1 ; writeen $end
$var wire 1 ! full $end
$var wire 1 " empty $end
$var reg 8 < buffer0 [7:0] $end
$var reg 8 = buffer1 [7:0] $end
$var reg 8 > buffer2 [7:0] $end
$var reg 8 ? buffer3 [7:0] $end
$var reg 8 @ buffer4 [7:0] $end
$var reg 8 A buffer5 [7:0] $end
$var reg 8 B buffer6 [7:0] $end
$var reg 8 C buffer7 [7:0] $end
$var reg 8 D dataout [7:0] $end
$var reg 5 E sp [4:0] $end
$upscope $end
$upscope $end
$enddefinitions $end
#0
$dumpvars
b0 E
b0 D
b0 C
b0 B
b0 A
b0 @
b0 ?
b0 >
b0 =
b0 <
0;
0:
09
08
07
06
05
04
03
02
b0 1
00
0/
0.
0-
0,
0+
0*
0)
0(
0'
0&
b0 %
0$
b0 #
1"
0!
$end
#50000
1$
#100000
0$
1(
#150000
1$
#200000
1)
1;
0$
1'
b1010 %
b1010 1
#250000
0"
0)
1*
b1010 <
b1 E
1$
#300000
0$
b10100 %
b10100 1
#350000
0*
1+
b10 E
b10100 =
1$
#400000
0$
b11110 %
b11110 1
#450000
0+
1,
b11110 >
b11 E
1$
#500000
0$
b101000 %
b101000 1
#550000
0,
1-
b100 E
b101000 ?
1$
#600000
0$
b110010 %
b110010 1
#650000
0-
1.
b110010 @
b101 E
1$
#700000
0$
b111100 %
b111100 1
#750000
0.
1/
b110 E
b111100 A
1$
#800000
0$
b1000110 %
b1000110 1
#850000
0/
10
b1000110 B
b111 E
1$
#900000
0$
b1010000 %
b1010000 1
#950000
0;
1!
00
b1000 E
b1010000 C
1$
#1000000
0$
b1011010 %
b1011010 1
#1050000
1$
#1100000
0$
0'
#1150000
1$
#1200000
19
1:
0$
1&
#1250000
0!
18
09
b1010000 #
b1010000 D
b111 E
1$
#1300000
0$
#1350000
17
08
b110 E
b1000110 #
b1000110 D
1$
#1400000
0$
#1450000
16
07
b111100 #
b111100 D
b101 E
1$
#1500000
0$
#1550000
15
06
b100 E
b110010 #
b110010 D
1$
#1600000
0$
#1650000
14
05
b101000 #
b101000 D
b11 E
1$
#1700000
0$
#1750000
13
04
b10 E
b11110 #
b11110 D
1$
#1800000
0$
#1850000
12
03
b10100 #
b10100 D
b1 E
1$
#1900000
0$
#1950000
0:
1"
02
b0 E
b1010 #
b1010 D
1$
