hw/제출용0511/parent.v
// 1. 상태를 정의한다.
// define => global variable이므로 다른 파일의 define과 겹치면 안 된다.
`define P0 2'b00 // sleep
`define P1 2'b01 // cook
`define P2 2'b10 // book

// 포트 정의
module parent (
    input clk,
    input resetb,
    input wakeup,
    output food,
    output book
);
    reg [1:0] state; 
    reg [1:0] next_state;
    reg food; 
    reg book; 

// 2. state logic
always @(negedge resetb or posedge clk)
    if(~resetb)
        state <= `P0;                // 리셋당하면 initial state로 돌아감.
    else 
        state <= next_state;

// 3. next state logic
always @(*)
    if(state == `P0)                // 수면 중
        if(wakeup == 1'b1)          // 깨어나세요
            next_state <= `P1;
        else
            next_state = `P0;
    else if(state == `P1)           // 밥 주기
        next_state <= `P2;
    else if(state == `P2)           // 공부시키기
        next_state <= `P0;
    else
        next_state <= state;

// 4. output logic
    // food 출력
always @(negedge resetb or posedge clk) begin
    if(~resetb) 
        food <= 1'b0;               // 초기화
    else if(state == `P1) 
        food <= 1'b1;               // 밥 출력
    else if(state == `P2) 
        food <= 1'b0;               // 밥 ㄴㄴ
end

    // book 출력
always @(negedge resetb or posedge clk) begin
    if(~resetb) 
        book <= 1'b0;               // 초기화
    else if(state == `P2) 
        book <= 1'b1;               // 책 출력
    else if (state == `P0) 
        book <= 1'b0;               // 책 ㄴㄴ
end

endmodule


/*
`define으로 상태 정의 (1) state space
구조가 위는 레벨트리거로 항상 상태를 바꾸고, 
아래는 엣지트리거로 상태를 샘플하는 거. (2) given condition
상태에 따라서 출력 (3) given state => out
*/

hw/제출용0511/kid.v
/*===============================*/
/*

1. define => state
2. state logic
3. next state logic
4. output logic

*/
/*================================*/

// 1. 상태를 먼저 정의
`define S0 2'b00 // hungry
`define S1 2'b01 // full
`define S2 2'b10 // study

// 포트를 정의
module kid (
    input clk,
    input resetb,
    input meal,
    input book,
    output request
);
    reg [1:0] state;
    reg [1:0] next_state;
    reg request;

// 2. state logic
    always @(negedge resetb or posedge clk)
        if(~resetb)
            state <= `S0;               // reset당하면 initial state로 돌아감.
        else
            state <= next_state;        // update from next_state

// 3. next state logic
    always @(*)
        if(state == `S0)                // 배고픔
            if(meal == 1'b1)
                next_state <= `S1;
            else
                next_state <= `S0;
        else if(state == `S1)           // 배부름
            if(book == 1'b1)
                next_state <= `S2;
            else
                next_state <= `S1;
        else if(state == `S2)           // 공부 중
            next_state <= `S0;
    

// 4. output logic
    always @(negedge resetb or posedge clk) begin
        if(~resetb)
            request <= 1'b0;        // 초기화
        else if(state == `S0)
            request <= 1'b1;        // 밥 요청.
        else if(state == `S1)
            request <= 1'b0;        // 밥 요청 멈춤.
    end

endmodule

hw/제출용0511/tb.v
module tb_testbench;

reg CLK, RESETB;

// wire MEAL, REQUEST, BOOK;

kid k1(
    .clk     (CLK),
    .resetb  (RESETB),
    .meal    (MEAL),
    .book    (BOOK),
    .request (REQUEST)
);

parent p1(
    .clk (CLK),
    .resetb (RESETB),
    .wakeup (REQUEST), 
    .food (MEAL),
    .book (BOOK)
);

// initial and finish time set
initial begin
    CLK     = 1'b0;
    RESETB  = 1'b0;    

    // $monitor($time, CLK, RESETB, " REQUEST : %b, MEAL : %b, BOOK : %b", REQUEST, MEAL, BOOK); 
    #`FTIME;
    $finish;
end

// dumpfile generate
initial begin
    $dumpfile("sim.vcd");
    $dumpvars(0, tb_testbench);  
end

// clock generate
always begin
    #50 CLK = ~CLK; // 100ns period pulse
end

// test condition
initial begin
    #500 RESETB = 1'b1; // reset release
    #300 RESETB = 1'b0;

    #200 RESETB = 1'b1;
end


endmodule

hw/제출용0511/sim.vcd
$date
	Thu May 11 15:37:51 2023
$end
$version
	Icarus Verilog
$end
$timescale
	1ps
$end
$scope module tb_testbench $end
$var wire 1 ! REQUEST $end
$var wire 1 " MEAL $end
$var wire 1 # BOOK $end
$var reg 1 $ CLK $end
$var reg 1 % RESETB $end
$scope module k1 $end
$var wire 1 $ clk $end
$var wire 1 % resetb $end
$var wire 1 " meal $end
$var wire 1 # book $end
$var reg 2 & next_state [1:0] $end
$var reg 1 ! request $end
$var reg 2 ' state [1:0] $end
$upscope $end
$scope module p1 $end
$var wire 1 $ clk $end
$var wire 1 % resetb $end
$var wire 1 ! wakeup $end
$var reg 1 # book $end
$var reg 1 " food $end
$var reg 2 ( next_state [1:0] $end
$var reg 2 ) state [1:0] $end
$upscope $end
$upscope $end
$enddefinitions $end
#0
$dumpvars
b0 )
b0 (
b0 '
b0 &
0%
0$
0#
0"
0!
$end
#50000
1$
#100000
0$
#150000
1$
#200000
0$
#250000
1$
#300000
0$
#350000
1$
#400000
0$
#450000
1$
#500000
0$
1%
#550000
b1 (
1!
1$
#600000
0$
#650000
b10 (
b1 )
1$
#700000
0$
#750000
b0 (
b1 &
b10 )
1"
1$
#800000
b0 &
0"
b0 )
0!
0$
0%
#850000
1$
#900000
0$
#950000
1$
#1000000
0$
1%
#1050000
b1 (
1!
1$
#1100000
0$
#1150000
b10 (
b1 )
1$
#1200000
0$
#1250000
b0 (
b1 &
b10 )
1"
1$
#1300000
0$
#1350000
b1 (
b10 &
1#
0"
b0 )
b1 '
1$
#1400000
0$
#1450000
b10 (
b0 &
b10 '
0!
b1 )
0#
1$
#1500000
0$
#1550000
b0 (
b1 &
1"
b10 )
b0 '
1$
#1600000
0$
#1650000
b1 (
b10 &
b1 '
1!
b0 )
0"
1#
1$
#1700000
0$
#1750000
b10 (
b0 &
0#
b1 )
0!
b10 '
1$
#1800000
0$
#1850000
b0 (
b1 &
b0 '
b10 )
1"
1$
#1900000
0$
#1950000
b1 (
b10 &
1#
0"
b0 )
1!
b1 '
1$
#2000000
0$
#2050000
b10 (
b0 &
b10 '
0!
b1 )
0#
1$
#2100000
0$
#2150000
b0 (
b1 &
1"
b10 )
b0 '
1$
#2200000
0$
#2250000
b1 (
b10 &
b1 '
1!
b0 )
0"
1#
1$
#2300000
0$
#2350000
b10 (
b0 &
0#
b1 )
0!
b10 '
1$
#2400000
0$
#2450000
b0 (
b1 &
b0 '
b10 )
1"
1$
#2500000
0$
#2550000
b1 (
b10 &
1#
0"
b0 )
1!
b1 '
1$
#2600000
0$
#2650000
b10 (
b0 &
b10 '
0!
b1 )
0#
1$
#2700000
0$
#2750000
b0 (
b1 &
1"
b10 )
b0 '
1$
#2800000
0$
#2850000
b1 (
b10 &
b1 '
1!
b0 )
0"
1#
1$
#2900000
0$
#2950000
b10 (
b0 &
0#
b1 )
0!
b10 '
1$
