hw/hw_week7/parent.v
// 1. 상태를 정의한다.
// define => global variable이므로 다른 파일의 define과 겹치면 안 된다.
`define P0 2'b01 // sleep
`define P1 2'b10 // cook
`define P2 2'b11 // book

// 포트 정의
module parent (
    input clk,
    input resetb,
    input wakeup,
    output food,
    output book
);
    reg [1:0] state; 
    reg [1:0] next_state;
    reg food; 
    reg book; 

// 2. 현재 FSM 내부에서 돌아가는 logic
always @(negedge resetb or posedge clk)
    if(~resetb)
        state <= `P0; // 리셋당하면 initial state로 돌아감.
    else 
        next_state <= state;

// 3. next state logic
always @(*)
    if(state == `P0)
        if(wakeup == 1'b1)
            next_state <= `P1;
        else
            next_state = `P0;
    else if(state == `P1)
        next_state <= `P2;
    else if(state == `P2)
        next_state <= `P0;
    else
        next_state <= state;

// 4. output logic
// always @(negedge resetb or posedge clk)
//     if(~resetb)
//         state <= `P0; // 리셋당하면 initial state로 돌아감.
//         food <= 1'b0; // 밥 그만 출력. 
//         book <= 1'b0; // 책 그만 출력.
//     else if (state == `P0)
//         food <= 1'b0; // 밥 그만 출력. 
//         book <= 1'b0; // 책 그만 출력.
//     else if(state == `P1)
//         food <= 1'b1; // 밥 출력.
//     else if(state == `P2)
//         food <= 1'b0; // 밥 그만 출력. 
//         book <= 1'b1; // 책 출력. 
//     else
//         food <= 1'b0; // 밥 그만 출력. 
//         book <= 1'b0; // 책 그만 출력.

always @(negedge resetb or posedge clk) begin
    if(~resetb) begin
        state <= `P0; // 리셋당하면 initial state로 돌아감.
        food <= 1'b0; // 밥 그만 출력. 
        book <= 1'b0; // 책 그만 출력.
    end
    else if (state == `P0) begin
        food <= 1'b0; // 밥 그만 출력. 
        book <= 1'b0; // 책 그만 출력.
    end
    else if(state == `P1) begin
        food <= 1'b1; // Output food.
        book <= 1'b0; // Stop book output.
    end
    else if(state == `P2) begin
        food <= 1'b0; // 밥 그만 출력. 
        book <= 1'b1; // 책 출력. 
    end
    else begin
        food <= 1'b0; // 밥 그만 출력. 
        book <= 1'b0; // 책 그만 출력.
    end
end

endmodule


/*
`define으로 상태 정의 (1) state space
구조가 위는 레벨트리거로 항상 상태를 바꾸고, 
아래는 엣지트리거로 상태를 샘플하는 거. (2) given condition
상태에 따라서 출력 (3) given state => out
*/

hw/hw_week7/kid.v
/*===============================*/
/*

1. 상태를 먼저 정의
2. 현재 FSM 내부에서 돌아가는 로직(status register)
3. next state logic
4. output logic

*/
/*================================*/

// 1. 상태를 먼저 정의
`define S0 2'b01 // hungry
`define S1 2'b10 // full
`define S2 2'b11 // study

// 포트를 정의
module kid (
    input clk,
    input resetb,
    input meal,
    input book,
    output request
);
    reg [1:0] state; // 현재상태
    reg [1:0] next_state;
    reg request; // !!! 출력은 reg로.

// 2. 현재 FSM 내부에서 돌아가는 로직
    always @(negedge resetb or posedge clk)
        if(~resetb)
            state <= `S0; // reset당하면 initial state로 돌아감.
        else
            state <= next_state; //update from next_state

// 3. next state logic
// 입력이 2개가 있고(meal, book), 입력이 있어야 바뀌는 상태 2개 입력없어도 시간에 따라 바뀔 상태 1개.
    always @(*)
        if(state == `S0) // 배가 고플 때(현재상태) => 밥을 먹고(입력) => 배가 불러짐(미래상태).
            if(meal == 1'b1)
                next_state <= `S1;
            else
                next_state <= `S0; // 밥없으면 => 여전히 배고픔.
        else if(state == `S1) // 배가 부르면 => 책을 먹고 => 배가 고파짐.
            if(book == 1'b1)
                next_state <= `S2;
            else
                next_state <= `S1; // 공부 안 하면 계속 배부름.
        else if(state == `S2) // 배가 고프면
            next_state <= `S0; // 시간 지남에 따라 배가 고파짐.
        else
            next_state <= state; // 혹시 모를 에러에 대비. 현재 반복.
    

// 4. output logic
    always @(negedge resetb or posedge clk) begin
        if(~resetb)
            request <= 1'b0;
        else if(state == `S0) // 배고픈 상태.
            request <= 1'b1; // 밥 줘.
        else if(state == `S1) // 배부른 상태.
            request <= 1'b0; // 밥ㄴㄴ.
    end

endmodule

hw/hw_week7/tb.v
module tb_testbench;

reg CLK, RESETB;

wire MEAL, REQUEST, BOOK;

kid k1(
    .clk     (CLK),
    .resetb  (RESETB),
    .meal    (MEAL),
    .book    (BOOK),
    .request (REQUEST)
);

parent p1(
    .clk (CLK),
    .resetb (RESETB),
    .wakeup (REQUEST), 
    .food (MEAL),
    .book (BOOK)
);


initial begin
    CLK     = 1'b0;
    RESETB  = 1'b0;    

    // $monitor($time, CLK, RESETB, " REQUEST : %b, MEAL : %b, BOOK : %b", REQUEST, MEAL, BOOK); 
    #`FTIME;
    $finish;
end

initial begin
    $dumpfile("sim.vcd");
    $dumpvars(0, tb_testbench);  
end

always begin
    #50 CLK = ~CLK; // 100ns period pulse
end

// test condition
initial begin
    #500 RESETB = 1'b1; // reset release
    #300 RESETB = 1'b0;

    #200 RESETB = 1'b1;
end


endmodule

hw/hw_week7/sim.vcd
$date
	Thu May 04 14:53:43 2023
$end
$version
	Icarus Verilog
$end
$timescale
	1ps
$end
$scope module tb_testbench $end
$var wire 1 ! REQUEST $end
$var wire 1 " MEAL $end
$var wire 1 # BOOK $end
$var reg 1 $ CLK $end
$var reg 1 % RESETB $end
$scope module k1 $end
$var wire 1 $ clk $end
$var wire 1 % resetb $end
$var wire 1 " meal $end
$var wire 1 # book $end
$var reg 2 & next_state [1:0] $end
$var reg 1 ! request $end
$var reg 2 ' state [1:0] $end
$upscope $end
$scope module p1 $end
$var wire 1 $ clk $end
$var wire 1 % resetb $end
$var wire 1 ! wakeup $end
$var reg 1 # book $end
$var reg 1 " food $end
$var reg 2 ( next_state [1:0] $end
$var reg 2 ) state [1:0] $end
$upscope $end
$upscope $end
$enddefinitions $end
$comment Show the parameter values. $end
$dumpall
$end
#0
$dumpvars
b0 )
b0 (
b0 '
b0 &
0%
0$
0#
0"
0!
$end
#50000
1$
#100000
0$
#150000
1$
#200000
0$
#250000
1$
#300000
0$
#350000
1$
#400000
0$
#450000
1$
#500000
0$
1%
#550000
b1 (
1!
1$
#600000
0$
#650000
b10 (
b1 )
1$
#700000
0$
#750000
b0 (
b1 &
b10 )
1"
1$
#800000
b0 &
0"
b0 )
0!
0$
0%
#850000
1$
#900000
0$
#950000
1$
#1000000
0$
1%
#1050000
b1 (
1!
1$
#1100000
0$
#1150000
b10 (
b1 )
1$
#1200000
0$
#1250000
b0 (
b1 &
b10 )
1"
1$
#1300000
0$
#1350000
b1 (
b10 &
1#
0"
b0 )
b1 '
1$
#1400000
0$
#1450000
b10 (
b0 &
b10 '
0!
b1 )
0#
1$
#1500000
0$
#1550000
b0 (
b1 &
1"
b10 )
b0 '
1$
#1600000
0$
#1650000
b1 (
b10 &
b1 '
1!
b0 )
0"
1#
1$
#1700000
0$
#1750000
b10 (
b0 &
0#
b1 )
0!
b10 '
1$
#1800000
0$
#1850000
b0 (
b1 &
b0 '
b10 )
1"
1$
#1900000
0$
#1950000
b1 (
b10 &
1#
0"
b0 )
1!
b1 '
1$
#2000000
0$
#2050000
b10 (
b0 &
b10 '
0!
b1 )
0#
1$
#2100000
0$
#2150000
b0 (
b1 &
1"
b10 )
b0 '
1$
#2200000
0$
#2250000
b1 (
b10 &
b1 '
1!
b0 )
0"
1#
1$
#2300000
0$
#2350000
b10 (
b0 &
0#
b1 )
0!
b10 '
1$
#2400000
0$
#2450000
b0 (
b1 &
b0 '
b10 )
1"
1$
#2500000
0$
#2550000
b1 (
b10 &
1#
0"
b0 )
1!
b1 '
1$
#2600000
0$
#2650000
b10 (
b0 &
b10 '
0!
b1 )
0#
1$
#2700000
0$
#2750000
b0 (
b1 &
1"
b10 )
b0 '
1$
#2800000
0$
#2850000
b1 (
b10 &
b1 '
1!
b0 )
0"
1#
1$
#2900000
0$
#2950000
b10 (
b0 &
0#
b1 )
0!
b10 '
1$
