ws_week3/03_adder/adder.v
module mux_2_1(a,s,y); // 2 by 1 mux 이름
input [1:0] a; // 리스트로 반복시켜 a를 두개 만들었다.
input s;
output y;

assign y = s ? a[1] : a[0];

endmodule

ws_week3/03_adder/adder_test.v
module mux_test(a,s,y);
output [1:0] a; // output 부터해야 잘 됨. 연결할 때 수월하게 하기 위해 이렇게 함.
output s;
input y;

// input 과 실행파일과 output을 이어주는 것들
reg [1:0] a; // 리스트로 2bits 변수를 선언
reg s;
wire y;

initial begin
    a[0] = 1'b0; // b stands for binary , 1 stands for 1-bit
    a[1] = 1'b0;
    s = 1'b0;
    #100 $finish; // 100ns에 끝난다.
end

always #40 a[0] =~ a[0]; // 무조건 40ns마다 다음 명령어 시행
always #20 a[1] =~ a[1];
always #10 s = ~s;

endmodule

ws_week3/03_adder_temp/adder_tb.v
module adder_tb();
// 다른파일과 연결할 wire
wire [1:0] n1;
wire n2, n3;

mux_test tester(n1, n2, n3); // a랑 s 가 밑으로 전달이 됨.

mux_2_1 dut (n1, n2, n3); // 윗줄의 n1, n2는 입력으로, n3는 다시 위로 출력

initial begin
    $dumpfile("tb_test_out.vcd");
    $dumpvars(0,dut);
end

endmodule

ws_week3/03_adder/tb_test_out.vcd
$date
	Sat Mar 18 13:42:25 2023
$end
$version
	Icarus Verilog
$end
$timescale
	1s
$end
$scope module adder_tb $end
$scope module dut $end
$var wire 1 ! y $end
$var wire 1 " s $end
$var wire 2 # a [1:0] $end
$upscope $end
$upscope $end
$enddefinitions $end
#0
$dumpvars
b0 #
0"
0!
$end
#10
1"
#20
0"
b10 #
#30
1!
1"
#40
0"
b1 #
#50
0!
1"
#60
1!
0"
b11 #
#70
1"
#80
0!
0"
b0 #
#90
1"
#100
0"
b10 #
