hw/pj5_floating/NumericalIntegral.v
`define N 64
`define CLOCK 5                             // 클럭 10ns 라고 생각하자. 계산이므로 샘플링을 많이 할수록 정확하다.

module numericalIntegral (
    input wire [3:0] test,
    input wire clk,
    input wire resetb,
    input wire [`N-1:0] signal_input,        // sampled signal this clock
    input wire start_integration,            // Start integration signal
    output reg [`N-1:0] integral_result      // Result of the integral
);

// Internal signals and variables
reg [`N-1:0] signal;
reg [`N-1:0] next_signal;

// Trapezoidal Rule computation
always @(posedge clk or negedge ~resetb) begin
    next_signal <= signal_input;
    signal <= next_signal;
end

always @(posedge clk or negedge ~resetb) begin
    if (~resetb) begin
        integral_result <= 0;
    end
    else if (start_integration) begin
        integral_result <= integral_result + (`CLOCK+`CLOCK)*(signal+next_signal)*0.5;
    end
end



endmodule

hw/pj5_floating/tb.v
module tb;

numericalIntegral inte(
    .test(TEST),
    .clk(CLK),
    .resetb(RESETB),
    .signal_input(SIGNAL_INPUT),
    .start_integration(START_INTEGRATION),
    .integral_result(INTEGRAL_RESULT)
);

reg [3:0] TEST;

reg CLK, RESETB;
reg [`N-1:0] SIGNAL_INPUT;
reg START_INTEGRATION;

wire [`N-1:0] INTEGRAL_RESULT;

initial begin
    #100 RESETB = 1'b1;
        
    #150 SIGNAL_INPUT = 2;
    #150 SIGNAL_INPUT = 4;
    #150 SIGNAL_INPUT = 6;
    #150 SIGNAL_INPUT = 8;
    #150 SIGNAL_INPUT = 10;
        
    #100 START_INTEGRATION = 1;

    #150 SIGNAL_INPUT = 2;
    #150 SIGNAL_INPUT = 4;
    #150 SIGNAL_INPUT = 6;
    #150 SIGNAL_INPUT = 8;
    #150 SIGNAL_INPUT = 10;
    #150 SIGNAL_INPUT = 10;
    #150 SIGNAL_INPUT = 10;
    #150 SIGNAL_INPUT = 10;

end

always begin
    #`CLOCK CLK = ~CLK;

end

initial begin
    CLK = 1'b0;
    RESETB  = 1'b0;
    SIGNAL_INPUT = 0;
    START_INTEGRATION = 0;

    #2000 $finish;
end

initial begin
    #10 TEST = 0;
    #10 TEST = 1;
    #10 TEST = 2;
    #10 TEST = 5;
    #10 TEST = 7;
    #10 TEST = 14;
    #10 TEST = 16;

end

initial begin
    $dumpfile("sim.vcd");
    $dumpvars(0, tb);  
end

endmodule //tb

hw/pj5_floating/sim.vcd
$date
	Fri May 19 17:51:02 2023
$end
$version
	Icarus Verilog
$end
$timescale
	1s
$end
$scope module tb $end
$var wire 64 ! INTEGRAL_RESULT [63:0] $end
$var reg 1 " CLK $end
$var reg 1 # RESETB $end
$var reg 64 $ SIGNAL_INPUT [63:0] $end
$var reg 1 % START_INTEGRATION $end
$var reg 4 & TEST [3:0] $end
$scope module inte $end
$var wire 1 " clk $end
$var wire 1 # resetb $end
$var wire 64 ' signal_input [63:0] $end
$var wire 1 % start_integration $end
$var wire 4 ( test [3:0] $end
$var reg 64 ) integral_result [63:0] $end
$var reg 64 * next_signal [63:0] $end
$var reg 64 + signal [63:0] $end
$upscope $end
$upscope $end
$enddefinitions $end
#0
$dumpvars
bx +
bx *
bx )
bx (
b0 '
bx &
0%
b0 $
0#
0"
bx !
$end
#5
b0 !
b0 )
b0 *
1"
#10
0"
b0 &
b0 (
#15
b0 +
1"
#20
0"
b1 &
b1 (
#25
1"
#30
0"
b10 &
b10 (
#35
1"
#40
0"
b101 &
b101 (
#45
1"
#50
0"
b111 &
b111 (
#55
1"
#60
0"
b1110 &
b1110 (
#65
1"
#70
0"
b0 &
b0 (
#75
1"
#80
0"
#85
1"
#90
0"
#95
1"
#100
0"
1#
#105
1"
#110
0"
#115
1"
#120
0"
#125
1"
#130
0"
#135
1"
#140
0"
#145
1"
#150
0"
#155
1"
#160
0"
#165
1"
#170
0"
#175
1"
#180
0"
#185
1"
#190
0"
#195
1"
#200
0"
#205
1"
#210
0"
#215
1"
#220
0"
#225
1"
#230
0"
#235
1"
#240
0"
#245
1"
#250
0"
b10 $
b10 '
#255
b10 *
1"
#260
0"
#265
b10 +
1"
#270
0"
#275
1"
#280
0"
#285
1"
#290
0"
#295
1"
#300
0"
#305
1"
#310
0"
#315
1"
#320
0"
#325
1"
#330
0"
#335
1"
#340
0"
#345
1"
#350
0"
#355
1"
#360
0"
#365
1"
#370
0"
#375
1"
#380
0"
#385
1"
#390
0"
#395
1"
#400
0"
b100 $
b100 '
#405
b100 *
1"
#410
0"
#415
b100 +
1"
#420
0"
#425
1"
#430
0"
#435
1"
#440
0"
#445
1"
#450
0"
#455
1"
#460
0"
#465
1"
#470
0"
#475
1"
#480
0"
#485
1"
#490
0"
#495
1"
#500
0"
#505
1"
#510
0"
#515
1"
#520
0"
#525
1"
#530
0"
#535
1"
#540
0"
#545
1"
#550
0"
b110 $
b110 '
#555
b110 *
1"
#560
0"
#565
b110 +
1"
#570
0"
#575
1"
#580
0"
#585
1"
#590
0"
#595
1"
#600
0"
#605
1"
#610
0"
#615
1"
#620
0"
#625
1"
#630
0"
#635
1"
#640
0"
#645
1"
#650
0"
#655
1"
#660
0"
#665
1"
#670
0"
#675
1"
#680
0"
#685
1"
#690
0"
#695
1"
#700
0"
b1000 $
b1000 '
#705
b1000 *
1"
#710
0"
#715
b1000 +
1"
#720
0"
#725
1"
#730
0"
#735
1"
#740
0"
#745
1"
#750
0"
#755
1"
#760
0"
#765
1"
#770
0"
#775
1"
#780
0"
#785
1"
#790
0"
#795
1"
#800
0"
#805
1"
#810
0"
#815
1"
#820
0"
#825
1"
#830
0"
#835
1"
#840
0"
#845
1"
#850
0"
b1010 $
b1010 '
#855
b1010 *
1"
#860
0"
#865
b1010 +
1"
#870
0"
#875
1"
#880
0"
#885
1"
#890
0"
#895
1"
#900
0"
#905
1"
#910
0"
#915
1"
#920
0"
#925
1"
#930
0"
#935
1"
#940
0"
#945
1"
#950
0"
1%
#955
b1100100 !
b1100100 )
1"
#960
0"
#965
b11001000 !
b11001000 )
1"
#970
0"
#975
b100101100 !
b100101100 )
1"
#980
0"
#985
b110010000 !
b110010000 )
1"
#990
0"
#995
b111110100 !
b111110100 )
1"
#1000
0"
#1005
b1001011000 !
b1001011000 )
1"
#1010
0"
#1015
b1010111100 !
b1010111100 )
1"
#1020
0"
#1025
b1100100000 !
b1100100000 )
1"
#1030
0"
#1035
b1110000100 !
b1110000100 )
1"
#1040
0"
#1045
b1111101000 !
b1111101000 )
1"
#1050
0"
#1055
b10001001100 !
b10001001100 )
1"
#1060
0"
#1065
b10010110000 !
b10010110000 )
1"
#1070
0"
#1075
b10100010100 !
b10100010100 )
1"
#1080
0"
#1085
b10101111000 !
b10101111000 )
1"
#1090
0"
#1095
b10111011100 !
b10111011100 )
1"
#1100
0"
b10 $
b10 '
#1105
b11001000000 !
b11001000000 )
b10 *
1"
#1110
0"
#1115
b11001111100 !
b11001111100 )
b10 +
1"
#1120
0"
#1125
b11010010000 !
b11010010000 )
1"
#1130
0"
#1135
b11010100100 !
b11010100100 )
1"
#1140
0"
#1145
b11010111000 !
b11010111000 )
1"
#1150
0"
#1155
b11011001100 !
b11011001100 )
1"
#1160
0"
#1165
b11011100000 !
b11011100000 )
1"
#1170
0"
#1175
b11011110100 !
b11011110100 )
1"
#1180
0"
#1185
b11100001000 !
b11100001000 )
1"
#1190
0"
#1195
b11100011100 !
b11100011100 )
1"
#1200
0"
#1205
b11100110000 !
b11100110000 )
1"
#1210
0"
#1215
b11101000100 !
b11101000100 )
1"
#1220
0"
#1225
b11101011000 !
b11101011000 )
1"
#1230
0"
#1235
b11101101100 !
b11101101100 )
1"
#1240
0"
#1245
b11110000000 !
b11110000000 )
1"
#1250
0"
b100 $
b100 '
#1255
b11110010100 !
b11110010100 )
b100 *
1"
#1260
0"
#1265
b11110110010 !
b11110110010 )
b100 +
1"
#1270
0"
#1275
b11111011010 !
b11111011010 )
1"
#1280
0"
#1285
b100000000010 !
b100000000010 )
1"
#1290
0"
#1295
b100000101010 !
b100000101010 )
1"
#1300
0"
#1305
b100001010010 !
b100001010010 )
1"
#1310
0"
#1315
b100001111010 !
b100001111010 )
1"
#1320
0"
#1325
b100010100010 !
b100010100010 )
1"
#1330
0"
#1335
b100011001010 !
b100011001010 )
1"
#1340
0"
#1345
b100011110010 !
b100011110010 )
1"
#1350
0"
#1355
b100100011010 !
b100100011010 )
1"
#1360
0"
#1365
b100101000010 !
b100101000010 )
1"
#1370
0"
#1375
b100101101010 !
b100101101010 )
1"
#1380
0"
#1385
b100110010010 !
b100110010010 )
1"
#1390
0"
#1395
b100110111010 !
b100110111010 )
1"
#1400
0"
b110 $
b110 '
#1405
b100111100010 !
b100111100010 )
b110 *
1"
#1410
0"
#1415
b101000010100 !
b101000010100 )
b110 +
1"
#1420
0"
#1425
b101001010000 !
b101001010000 )
1"
#1430
0"
#1435
b101010001100 !
b101010001100 )
1"
#1440
0"
#1445
b101011001000 !
b101011001000 )
1"
#1450
0"
#1455
b101100000100 !
b101100000100 )
1"
#1460
0"
#1465
b101101000000 !
b101101000000 )
1"
#1470
0"
#1475
b101101111100 !
b101101111100 )
1"
#1480
0"
#1485
b101110111000 !
b101110111000 )
1"
#1490
0"
#1495
b101111110100 !
b101111110100 )
1"
#1500
0"
#1505
b110000110000 !
b110000110000 )
1"
#1510
0"
#1515
b110001101100 !
b110001101100 )
1"
#1520
0"
#1525
b110010101000 !
b110010101000 )
1"
#1530
0"
#1535
b110011100100 !
b110011100100 )
1"
#1540
0"
#1545
b110100100000 !
b110100100000 )
1"
#1550
0"
b1000 $
b1000 '
#1555
b110101011100 !
b110101011100 )
b1000 *
1"
#1560
0"
#1565
b110110100010 !
b110110100010 )
b1000 +
1"
#1570
0"
#1575
b110111110010 !
b110111110010 )
1"
#1580
0"
#1585
b111001000010 !
b111001000010 )
1"
#1590
0"
#1595
b111010010010 !
b111010010010 )
1"
#1600
0"
#1605
b111011100010 !
b111011100010 )
1"
#1610
0"
#1615
b111100110010 !
b111100110010 )
1"
#1620
0"
#1625
b111110000010 !
b111110000010 )
1"
#1630
0"
#1635
b111111010010 !
b111111010010 )
1"
#1640
0"
#1645
b1000000100010 !
b1000000100010 )
1"
#1650
0"
#1655
b1000001110010 !
b1000001110010 )
1"
#1660
0"
#1665
b1000011000010 !
b1000011000010 )
1"
#1670
0"
#1675
b1000100010010 !
b1000100010010 )
1"
#1680
0"
#1685
b1000101100010 !
b1000101100010 )
1"
#1690
0"
#1695
b1000110110010 !
b1000110110010 )
1"
#1700
0"
b1010 $
b1010 '
#1705
b1001000000010 !
b1001000000010 )
b1010 *
1"
#1710
0"
#1715
b1001001011100 !
b1001001011100 )
b1010 +
1"
#1720
0"
#1725
b1001011000000 !
b1001011000000 )
1"
#1730
0"
#1735
b1001100100100 !
b1001100100100 )
1"
#1740
0"
#1745
b1001110001000 !
b1001110001000 )
1"
#1750
0"
#1755
b1001111101100 !
b1001111101100 )
1"
#1760
0"
#1765
b1010001010000 !
b1010001010000 )
1"
#1770
0"
#1775
b1010010110100 !
b1010010110100 )
1"
#1780
0"
#1785
b1010100011000 !
b1010100011000 )
1"
#1790
0"
#1795
b1010101111100 !
b1010101111100 )
1"
#1800
0"
#1805
b1010111100000 !
b1010111100000 )
1"
#1810
0"
#1815
b1011001000100 !
b1011001000100 )
1"
#1820
0"
#1825
b1011010101000 !
b1011010101000 )
1"
#1830
0"
#1835
b1011100001100 !
b1011100001100 )
1"
#1840
0"
#1845
b1011101110000 !
b1011101110000 )
1"
#1850
0"
#1855
b1011111010100 !
b1011111010100 )
1"
#1860
0"
#1865
b1100000111000 !
b1100000111000 )
1"
#1870
0"
#1875
b1100010011100 !
b1100010011100 )
1"
#1880
0"
#1885
b1100100000000 !
b1100100000000 )
1"
#1890
0"
#1895
b1100101100100 !
b1100101100100 )
1"
#1900
0"
#1905
b1100111001000 !
b1100111001000 )
1"
#1910
0"
#1915
b1101000101100 !
b1101000101100 )
1"
#1920
0"
#1925
b1101010010000 !
b1101010010000 )
1"
#1930
0"
#1935
b1101011110100 !
b1101011110100 )
1"
#1940
0"
#1945
b1101101011000 !
b1101101011000 )
1"
#1950
0"
#1955
b1101110111100 !
b1101110111100 )
1"
#1960
0"
#1965
b1110000100000 !
b1110000100000 )
1"
#1970
0"
#1975
b1110010000100 !
b1110010000100 )
1"
#1980
0"
#1985
b1110011101000 !
b1110011101000 )
1"
#1990
0"
#1995
b1110101001100 !
b1110101001100 )
1"
