ws_week7/02_kid_parent/parent.v
`define P0 0 // sleep
`define P1 1 // cook
// ㄴ global variable이므로 다른 파일의 define과 겹치면 안 된다.

module parent (
    input clk,
    input resetb,
    input wakeup,
    output food
);
    reg state; 
    reg next_state;
    reg food; 

// next state determination
    always @(*)
        if(state == `P0) // sleep(default)
            if(wakeup == 1'b1)
                next_state <= `P1; // cook
            else
                next_state <= `P0;
        else if(state == `P1)
            if(wakeup == 1'b1)
                next_state <= `P1; // repeat wakeup
            else
                next_state <= `P0; // stop meal, lets sleep
        else
            next_state <= state;
    
// So, final state may be set a rising clock.
    always @(negedge resetb or posedge clk)
        if(~resetb)
            state <= `P0;
        else if(state == `P1)
            food <= 1'b1; // eat my food
        else
            food <= 1'b0; // cut food

// given state, lets define output
always @(negedge resetb or posedge clk) begin
    if(~resetb)
        food <= 1'b0;
    else if(state == `P0)
        food <= 1'b1; // please give me meal
    else if(state == `P1)
        food <= 1'b0; // don't feed me. im full
end

endmodule


/*
`define으로 상태 정의 (1) state space
구조가 위는 레벨트리거로 항상 상태를 바꾸고, 
아래는 엣지트리거로 상태를 샘플하는 거. (2) given condition
상태에 따라서 출력 (3) given state => out
*/

ws_week7/02_kid_parent/kid.v
`define S0 0 // hungry
`define S1 1 // full
// ㄴ상태 정함.

module kid (
    input clk,
    input resetb,
    input meal,
    output request
);
    reg state; // 현재상태
    reg next_state;
    reg request; // !!! 출력은 reg로.

// next state determination
    always @(*)
        if(state == `S0) // 배가 고플 때(현재상태) => 밥을 먹고(입력) => 배가 불러짐(미래상태).
            if(meal == 1'b1)
                next_state <= `S1;
            else
                next_state <= `S0; // 밥없으면 => 여전히 배고픔.
        else if(state == `S1) // 아직 배가 고프면
            next_state <= `S0; // on elasped time, become hungry
        else
            next_state <= state;
    
// So, final state may be set a rising clock.
    always @(negedge resetb or posedge clk)
        if(~resetb)
            state <= `S0; // on birth, i am hungry
        else
            state <= next_state; //update from next_state

// given state, lets define output
always @(negedge resetb or posedge clk) begin
    if(~resetb)
        request <= 1'b0;
    else if(state == `S0)
        request <= 1'b1; // please give me meal
    else if(state == `S1)
        request <= 1'b0; // don't feed me. im full
end

endmodule


/*
`define으로 상태 정의 (1) state space
구조가 위는 레벨트리거로 항상 상태를 바꾸고, 
아래는 엣지트리거로 상태를 샘플하는 거. (2) given condition
상태에 따라서 출력 (3) given state => out
*/

ws_week7/02_kid_parent/tb.v
/*
https://jamboard.google.com/d/1-HRD5jC9OJBApIVmR7xz3oLNlFpbC5Wj01Q-bl0ocPk/edit?usp=sharing
*/

module tb_testbench;

reg CLK, RESETB;

wire MEAL, REQUEST;

kid k1(
    .clk     (CLK),
    .resetb  (RESETB),
    .meal    (MEAL),
    .request (REQUEST)
);

parent p1(
    .clk (CLK),
    .resetb (RESETB),
    .wakeup (REQUEST), // !!!!
    .food (MEAL) // !!!!
);


initial begin
    CLK     = 1'b0;
    RESETB  = 1'b0;
    // MEAL = 1'b0; 얘네는 설정하면 안 된담. wire라서
    // REQUEST = 1'b0;

    $monitor($time, CLK,  RESETB, MEAL, REQUEST);
    #`FTIME;
    $finish;
end


// test condition
initial begin
    #150 RESETB = 1'b1; // reset release
end


always begin
    #50 CLK = ~CLK; // 100ns period pulse
end


initial begin
    $dumpfile("sim.vcd");
    $dumpvars(0, tb_testbench);  
end


endmodule

ws_week7/02_kid_parent/sim.vcd
$date
	Fri May 12 15:28:35 2023
$end
$version
	Icarus Verilog
$end
$timescale
	1ps
$end
$scope module tb_testbench $end
$var wire 1 ! REQUEST $end
$var wire 1 " MEAL $end
$var reg 1 # CLK $end
$var reg 1 $ RESETB $end
$scope module k1 $end
$var wire 1 # clk $end
$var wire 1 $ resetb $end
$var wire 1 " meal $end
$var reg 1 % next_state $end
$var reg 1 ! request $end
$var reg 1 & state $end
$upscope $end
$scope module p1 $end
$var wire 1 # clk $end
$var wire 1 $ resetb $end
$var wire 1 ! wakeup $end
$var reg 1 " food $end
$var reg 1 ' next_state $end
$var reg 1 ( state $end
$upscope $end
$upscope $end
$enddefinitions $end
#0
$dumpvars
0(
0'
0&
0%
0$
0#
x"
0!
$end
#50000
1#
#100000
0#
#150000
1'
1!
0"
1#
1$
#200000
0#
#250000
1(
1#
#300000
0#
#350000
1%
1"
1#
#400000
0#
#450000
0%
1&
1#
#500000
0#
#550000
1%
0'
0&
0!
1#
#600000
0#
#650000
1'
0%
0(
1!
1&
1#
#700000
0#
#750000
0'
0&
0!
1(
0"
1#
#800000
0#
#850000
1%
1'
1"
0(
1!
1#
#900000
0#
#950000
0%
1&
1(
0"
1#
#1000000
0#
#1050000
0'
1%
1"
0!
0&
1#
#1100000
0#
#1150000
0%
1'
1&
1!
0(
1#
#1200000
0#
#1250000
0'
0"
1(
0!
0&
1#
#1300000
0#
#1350000
1'
1%
1!
0(
1"
1#
#1400000
0#
#1450000
0%
0"
1(
1&
1#
#1500000
0#
#1550000
0'
1%
0&
0!
1"
1#
#1600000
0#
#1650000
1'
0%
0(
1!
1&
1#
#1700000
0#
#1750000
0'
0&
0!
1(
0"
1#
#1800000
0#
#1850000
1%
1'
1"
0(
1!
1#
#1900000
0#
#1950000
0%
1&
1(
0"
1#
#2000000
0#
#2050000
0'
1%
1"
0!
0&
1#
#2100000
0#
#2150000
0%
1'
1&
1!
0(
1#
#2200000
0#
#2250000
0'
0"
1(
0!
0&
1#
#2300000
0#
#2350000
1'
1%
1!
0(
1"
1#
#2400000
0#
#2450000
0%
0"
1(
1&
1#
#2500000
0#
#2550000
0'
1%
0&
0!
1"
1#
#2600000
0#
#2650000
1'
0%
0(
1!
1&
1#
#2700000
0#
#2750000
0'
0&
0!
1(
0"
1#
#2800000
0#
#2850000
1%
1'
1"
0(
1!
1#
#2900000
0#
#2950000
0%
1&
1(
0"
1#
