ws_week7/01_watch/counter.v
module counter(
    input clk,
    input reset_b,
    input enable,
    input read,
    output [7:0] data
);

reg [7:0] count;

assign data = read ? count : 8'bz;




always @(negedge reset_b or posedge clk)
    if(~reset_b)
        count <= 8'b0; 
    else if(enable)
        count <= count + 1;
endmodule

ws_week7/01_watch/watch.v
module watch(
    input       clk,
    input       reset_b,
    input       read, // !!!!!
    input       enable,
    input       capture,
    output [7:0] duration //정보받아야하는데 플로팅.
);

// counter모듈에서 받는 정보는 wire로.
wire [7:0] count;

reg [7:0] captured;
reg [7:0] duration; //reg로 만들면 플로팅 방지.

wire read_cnt;
assign read_cnt = read | capture; // 출력단의 count가 동작할 조건 변경.

counter cnt(
    .clk(clk),
    .reset_b(reset_b),
    .enable(enable),
    .read(read_cnt),
    .data(count)
);

always @(negedge reset_b or posedge clk)
    if(~reset_b)
        captured <= 0; // !!!!!
    else if(capture)
        // capture 할 때 count 값 불러오기.
        captured <= count;

always @(negedge reset_b or posedge clk)
    if(~reset_b)
        duration <= 8'b0; // !!!! 이름 안 바꿨었음. 8'b0랑 0이랑 차이없음.
    else if(read)
        // capture 할 때 count 값 불러오기.
        duration <= count - captured;
endmodule

ws_week7/01_stopwatch/old.tb.v
module tb_testbench;


reg CLK, RESET_B, ENABLE, CAPTURE, READ;
wire [7:0] DURATION;
watch wt(
    .clk     (CLK),
    .reset_b  (RESET_B),
    .enable  (ENABLE),
    .read    (READ),
    .capture (CAPTURE),
    .duration(DURATION)
);


initial begin
    CLK     = 1'b0;
    RESET_B  = 1'b0;
    ENABLE  = 1'b0;
    READ    = 1'b0;
    CAPTURE = 1'b0; // !!!! 초기화해야 정보를 잘 받는다.

    $monitor($time, CLK,  RESET_B, ENABLE, READ);
    #`FTIME;
    $finish;
end


// test condition
initial begin
    #150 RESET_B = 1'b1; // reset release
    #100 ENABLE = 1'b1; // 250ns from zero time

    #100 CAPTURE = 1'b1;

    #410 READ   = 1'b1;
    #410 READ   = 1'b0;
    #410 READ   = 1'b1;
    #110 READ   = 1'b0;
    
    #100

    #410 CAPTURE   = 1'b1;
    #410 CAPTURE   = 1'b0;

    #200

    #410 READ   = 1'b1;
    #110 READ   = 1'b0;

/*
setup margin, hold margin이 없으면 violation 발생.
근데 이러면 40ns밀리는거 아닌가...?
    #400 READ   = 1'b1;
    #400 READ   = 1'b0;
    #400 READ   = 1'b1;
    #100 READ   = 1'b0;
*/
end


always begin
    #50 CLK = ~CLK; // 100ns period pulse
end


initial begin
    $dumpfile("old.sim.vcd");
    $dumpvars(0, tb_testbench);  
end


endmodule

ws_week7/01_stopwatch/sim.vcd
$date
	Fri Apr 28 16:04:00 2023
$end
$version
	Icarus Verilog
$end
$timescale
	1ps
$end
$scope module tb_testbench $end
$var wire 8 ! DURATION [7:0] $end
$var reg 1 " CAPTURE $end
$var reg 1 # CLK $end
$var reg 1 $ ENABLE $end
$var reg 1 % READ $end
$var reg 1 & RESET_B $end
$scope module wt $end
$var wire 1 " capture $end
$var wire 1 # clk $end
$var wire 1 $ enable $end
$var wire 1 % read $end
$var wire 1 ' read_cnt $end
$var wire 1 & reset_b $end
$var wire 8 ( count [7:0] $end
$var reg 8 ) captured [7:0] $end
$var reg 8 * duration [7:0] $end
$scope module cnt $end
$var wire 1 # clk $end
$var wire 1 $ enable $end
$var wire 1 ' read $end
$var wire 1 & reset_b $end
$var wire 8 + data [7:0] $end
$var reg 8 , count [7:0] $end
$upscope $end
$upscope $end
$upscope $end
$enddefinitions $end
#0
$dumpvars
b0 ,
bz +
b0 *
b0 )
bz (
0'
0&
0%
0$
0#
0"
b0 !
$end
#50000
1#
#100000
0#
#150000
1#
1&
#200000
0#
#250000
b1 ,
1#
1$
#300000
0#
#350000
b10 ,
bz )
b10 (
b10 +
1'
1#
1"
#400000
0#
#450000
b11 (
b11 +
b10 )
b11 ,
1#
#500000
0#
#550000
b100 (
b100 +
b100 ,
b11 )
1#
#600000
0#
#650000
b101 (
b101 +
b100 )
b101 ,
1#
#700000
0#
#750000
b110 (
b110 +
b110 ,
b101 )
1#
#760000
1%
#800000
0#
#850000
b111 (
b111 +
b1 !
b1 *
b110 )
b111 ,
1#
#900000
0#
#950000
b1000 (
b1000 +
b1000 ,
b111 )
1#
#1000000
0#
#1050000
b1001 (
b1001 +
b1000 )
b1001 ,
1#
#1100000
0#
#1150000
b1010 (
b1010 +
b1010 ,
b1001 )
1#
#1170000
0%
#1200000
0#
#1250000
b1011 (
b1011 +
b1010 )
b1011 ,
1#
#1300000
0#
#1350000
b1100 (
b1100 +
b1100 ,
b1011 )
1#
#1400000
0#
#1450000
b1101 (
b1101 +
b1100 )
b1101 ,
1#
#1500000
0#
#1550000
b1110 (
b1110 +
b1110 ,
b1101 )
1#
#1580000
1%
#1600000
0#
#1650000
b1111 (
b1111 +
b1110 )
b1111 ,
1#
#1690000
0%
#1700000
0#
#1750000
b10000 (
b10000 +
b10000 ,
b1111 )
1#
#1800000
0#
#1850000
b10001 (
b10001 +
b10000 )
b10001 ,
1#
#1900000
0#
#1950000
b10010 (
b10010 +
b10010 ,
b10001 )
1#
#2000000
0#
#2050000
b10011 (
b10011 +
b10010 )
b10011 ,
1#
#2100000
0#
#2150000
b10100 (
b10100 +
b10100 ,
b10011 )
1#
#2200000
0#
#2250000
b10101 (
b10101 +
b10100 )
b10101 ,
1#
#2300000
0#
#2350000
b10110 (
b10110 +
b10110 ,
b10101 )
1#
#2400000
0#
#2450000
b10111 (
b10111 +
b10110 )
b10111 ,
1#
#2500000
0#
#2550000
b11000 (
b11000 +
b11000 ,
b10111 )
1#
#2600000
0#
#2610000
bz (
bz +
0'
0"
#2650000
b11001 ,
1#
#2700000
0#
#2750000
b11010 ,
1#
#2800000
0#
#2850000
b11011 ,
1#
#2900000
0#
#2950000
b11100 ,
1#
