ws_week6/01_counter/counter.v
/* 
수업시간 칠판
https://docs.google.com/document/d/1pqUUXyV-446H0wwRoOOWJEajvgDLcEONUzW6a7cfHFk/edit
*/
module counter(
    input clk,
    input reset_b,
    input enable,
    input read,
    output [7:0] data
);

reg [7:0] count;
// wire [7:0] data;

assign data = read ? count : 8'bz; // floating 상태로 만들어야 신호를 왜곡없이 입력해줄 수 있다.

// FF으로 설계된.(negedge, posedge)
always @(negedge reset_b or posedge clk) // negative edge에서~
    if(~reset_b)
        // 실제로는 8bits의 flip-flop이 전체적으로 초기화 되기 충분한 시간이 필요하다. setup margin, setup violation(불완전한 데이터가 전달되는 것)
        count <= 8'b11; // 0을 7개 채우면 부족해서 error인건 알겠는데, 0말고 11넣으면 3으로 보는지 11로 볼지.
    else if(enable)
        count <= count + 1;
    // else 없어도 된다.
endmodule

// <= nonblocking : 동시에 출발한다
// = blocking : 차례대로 출발한다
// 시간에 따라 바꿔나가는 회로 = sequiential circuit

ws_week6/01_counter/tb.v
`timescale 1ns/1ps
// counter 2개가 1개의 data bus에 올라간걸 구현 => 다른 시간 대에 read하면 된다.

module tb;

// stimulus => 시간에 따라 바뀜 => reg로 설정
reg CLK;
reg RESET_B;
reg ENABLE1;
reg ENABLE2;
reg READ1;
reg READ2;
wire [7:0] DATA;

counter cnt1(
    .clk(CLK),
    .reset_b(RESET_B),
    .enable(ENABLE1),
    .read(READ1),
    .data(DATA)
);

counter cnt2(
    .clk(CLK),
    .reset_b(RESET_B),
    .enable(ENABLE2),
    .read(READ2),
    .data(DATA)
);

initial begin
    CLK     = 1'b0;
    RESET_B = 1'b0;
    ENABLE1  = 1'b0;
    READ1    = 1'b0;
    ENABLE2  = 1'b0;
    READ2    = 1'b0;

    #2000
    $finish;
end

// 
initial begin
    #150 RESET_B    = 1'b1; // reset release
    #100 ENABLE1     = 1'b1; // 250ns from zero time
    #400 READ1       = 1'b1;
    RESET_B = 1'b0;
    #100 READ1       = 1'b0;
    #500 READ1       = 1'b1;
    #100 READ1       = 1'b0;
end

initial begin
    #150 RESET_B    = 1'b1; // reset release
    #200 ENABLE2     = 1'b1; // 250ns from zero time
    #700 READ2       = 1'b1;
    #100 READ2       = 1'b0;
    #100 READ2       = 1'b1; // unknown-x 나도록 같은 시간대에 read하기
    #100 READ2       = 1'b0;
end

always begin
    #50 CLK = ~CLK; // 100ns period pulse
end

initial begin
    $monitor("tick : %3d : reset_b : %b, enable : %b, read : %b, data : %b", $time, RESET_B, ENABLE1, READ1, DATA); 

end

initial begin
    $dumpfile("sim.vcd");
    // dumpfile로 모듈 하나말고 tb전체 볼 수 있다.
    $dumpvars(0,tb);
end

endmodule

ws_week6/01_counter/sim.vcd
$date
	Fri Apr  7 19:14:48 2023
$end
$version
	Icarus Verilog
$end
$timescale
	1ps
$end
$scope module tb $end
$var wire 8 ! DATA [7:0] $end
$var reg 1 " CLK $end
$var reg 1 # ENABLE1 $end
$var reg 1 $ ENABLE2 $end
$var reg 1 % READ1 $end
$var reg 1 & READ2 $end
$var reg 1 ' RESET_B $end
$scope module cnt1 $end
$var wire 1 " clk $end
$var wire 8 ( data [7:0] $end
$var wire 1 # enable $end
$var wire 1 % read $end
$var wire 1 ' reset_b $end
$var reg 8 ) count [7:0] $end
$upscope $end
$scope module cnt2 $end
$var wire 1 " clk $end
$var wire 8 * data [7:0] $end
$var wire 1 $ enable $end
$var wire 1 & read $end
$var wire 1 ' reset_b $end
$var reg 8 + count [7:0] $end
$upscope $end
$upscope $end
$enddefinitions $end
#0
$dumpvars
b11 +
bz *
b11 )
bz (
0'
0&
0%
0$
0#
0"
bz !
$end
#50000
1"
#100000
0"
#150000
1"
1'
#200000
0"
#250000
b100 )
1"
1#
#300000
0"
#350000
b101 )
b100 +
1"
1$
#400000
0"
#450000
b101 +
b110 )
1"
#500000
0"
#550000
b111 )
b110 +
1"
#600000
0"
#650000
b11 +
b11 )
b11 !
b11 (
b11 *
1"
0'
1%
#700000
0"
#750000
bz !
bz (
bz *
1"
0%
#800000
0"
#850000
1"
#900000
0"
#950000
1"
#1000000
0"
#1050000
b11 !
b11 (
b11 *
1"
1&
#1100000
0"
#1150000
bz !
bz (
bz *
1"
0&
#1200000
0"
#1250000
b11 !
b11 (
b11 *
1"
1&
1%
#1300000
0"
#1350000
bz !
bz (
bz *
1"
0&
0%
